adafruit_uc8179.py
adafruit_circuitpython_uc8179-1.0.1.dist-info/licenses/LICENSE
adafruit_circuitpython_uc8179-1.0.1.dist-info/METADATA
adafruit_circuitpython_uc8179-1.0.1.dist-info/WHEEL
adafruit_circuitpython_uc8179-1.0.1.dist-info/top_level.txt
adafruit_circuitpython_uc8179-1.0.1.dist-info/RECORD
