Metadata-Version: 2.4
Name: adafruit-circuitpython-uc8179
Version: 1.0.1
Summary: CircuitPython `displayio` driver for UC8151D-based ePaper dis
Author-email: Adafruit Industries <circuitpython@adafruit.com>
License: MIT
Project-URL: Homepage, https://github.com/adafruit/Adafruit_CircuitPython_UC8179
Keywords: adafruit,blinka,circuitpython,micropython,uc8179,UC8179,epaper
Classifier: Intended Audience :: Developers
Classifier: Topic :: Software Development :: Libraries
Classifier: Topic :: Software Development :: Embedded Systems
Classifier: Topic :: System :: Hardware
Classifier: License :: OSI Approved :: MIT License
Classifier: Programming Language :: Python :: 3
License-File: LICENSE
Requires-Dist: Adafruit-Blinka
Provides-Extra: optional
Dynamic: license-file
